dnacrypt/__init__.py
dnacrypt/cli.py
dnacrypt/interpreter.py
dnacrypt/lexer.py
dnacrypt/parser.py
dnacrypt/semantic.py
dnacrypt/stdlib/__init__.py
dnacrypt/stdlib/crypto.py
dnacrypt/stdlib/dna.py
dnacrypt_lang-1.0.2.dist-info/licenses/LICENSE
dnacrypt_lang-1.0.2.dist-info/METADATA
dnacrypt_lang-1.0.2.dist-info/WHEEL
dnacrypt_lang-1.0.2.dist-info/entry_points.txt
dnacrypt_lang-1.0.2.dist-info/top_level.txt
dnacrypt_lang-1.0.2.dist-info/RECORD
