Metadata-Version: 2.4
Name: dnacrypt-lang
Version: 1.0.2
Summary: A domain-specific programming language for DNA-based cryptography
Home-page: https://github.com/yourusername/dnacrypt
Author: Harshith
Author-email: Harshith Madhavaram <madhavaram.harshith2412@gmail.com>
License: MIT
Keywords: cryptography,dna,bioinformatics,programming-language
Classifier: Development Status :: 4 - Beta
Classifier: Intended Audience :: Developers
Classifier: Topic :: Security :: Cryptography
Requires-Python: >=3.8
License-File: LICENSE
Requires-Dist: cryptography>=41.0.0
Dynamic: author
Dynamic: home-page
Dynamic: license-file
Dynamic: requires-python
